allintrophy/__init__.py
allintrophy/static/applause4.wav
allintrophy/static/curtains.png
allintrophy/static/drum3.glb
allintrophy/static/index.html
allintrophy/static/main.css
allintrophy/static/main.js
allintrophy-0.0.5.dist-info/METADATA
allintrophy-0.0.5.dist-info/RECORD
allintrophy-0.0.5.dist-info/WHEEL
allintrophy-0.0.5.dist-info/top_level.txt
