Metadata-Version: 2.1
Name: allintrophy
Version: 0.0.5
Summary: Trophy Case App for All-Inspiration
Home-page: UNKNOWN
Author: Hugo Wainwright
Author-email: wainwrighthugo@gmail.com
License: UNKNOWN
Keywords: sc2,trophy
Platform: UNKNOWN
Requires-Dist: flask
